pbparam/__init__.py
pbparam/optimisation_result.py
pbparam/version.py
pbparam/cost_functions/__init__.py
pbparam/cost_functions/base_cost_function.py
pbparam/cost_functions/mle.py
pbparam/cost_functions/rmse.py
pbparam/input/data/C3_1C_profile_25deg.csv
pbparam/input/data/LGM50_789_1C_25degC.csv
pbparam/input/data/anode_OCP_2_delit.csv
pbparam/input/data/anode_OCP_2_lit.csv
pbparam/input/data/anode_OCP_3_delit.csv
pbparam/input/data/anode_OCP_3_lit.csv
pbparam/input/data/cathode_OCP_2_delit.csv
pbparam/input/data/cathode_OCP_2_lit.csv
pbparam/input/data/cathode_OCP_3_delit.csv
pbparam/input/data/cathode_OCP_3_lit.csv
pbparam/input/data/GITT/pulse_1.csv
pbparam/input/data/GITT/pulse_10.csv
pbparam/input/data/GITT/pulse_11.csv
pbparam/input/data/GITT/pulse_12.csv
pbparam/input/data/GITT/pulse_13.csv
pbparam/input/data/GITT/pulse_14.csv
pbparam/input/data/GITT/pulse_15.csv
pbparam/input/data/GITT/pulse_16.csv
pbparam/input/data/GITT/pulse_17.csv
pbparam/input/data/GITT/pulse_18.csv
pbparam/input/data/GITT/pulse_19.csv
pbparam/input/data/GITT/pulse_2.csv
pbparam/input/data/GITT/pulse_20.csv
pbparam/input/data/GITT/pulse_21.csv
pbparam/input/data/GITT/pulse_22.csv
pbparam/input/data/GITT/pulse_23.csv
pbparam/input/data/GITT/pulse_24.csv
pbparam/input/data/GITT/pulse_25.csv
pbparam/input/data/GITT/pulse_26.csv
pbparam/input/data/GITT/pulse_27.csv
pbparam/input/data/GITT/pulse_28.csv
pbparam/input/data/GITT/pulse_29.csv
pbparam/input/data/GITT/pulse_3.csv
pbparam/input/data/GITT/pulse_30.csv
pbparam/input/data/GITT/pulse_31.csv
pbparam/input/data/GITT/pulse_32.csv
pbparam/input/data/GITT/pulse_33.csv
pbparam/input/data/GITT/pulse_34.csv
pbparam/input/data/GITT/pulse_35.csv
pbparam/input/data/GITT/pulse_36.csv
pbparam/input/data/GITT/pulse_37.csv
pbparam/input/data/GITT/pulse_38.csv
pbparam/input/data/GITT/pulse_39.csv
pbparam/input/data/GITT/pulse_4.csv
pbparam/input/data/GITT/pulse_40.csv
pbparam/input/data/GITT/pulse_5.csv
pbparam/input/data/GITT/pulse_6.csv
pbparam-0.1.dist-info/METADATA
pbparam-0.1.dist-info/WHEEL
pbparam-0.1.dist-info/licenses/LICENSE
pbparam-0.1.dist-info/RECORD
