Metadata-Version: 2.1
Name: pbparam
Version: 0.1
Summary: A package for optimising parameters in PyBaMM. Under development.
Author: Muhammed Sogut, W. Dhammika Widanage, Philip Grylls
Author-email: Ferran Brosa Planella <Ferran.Brosa-Planella@warwick.ac.uk>
License-Expression: BSD-3-Clause
License-File: LICENSE
Requires-Dist: matplotlib
Requires-Dist: pybamm
Provides-Extra: deploy
Requires-Dist: bump2version; extra == 'deploy'
Provides-Extra: dev
Requires-Dist: black; extra == 'dev'
Requires-Dist: coverage; extra == 'dev'
Requires-Dist: flake8>=3; extra == 'dev'
Requires-Dist: nox; extra == 'dev'
Provides-Extra: docs
Requires-Dist: guzzle-sphinx-theme; extra == 'docs'
Requires-Dist: sphinx-rtd-theme; extra == 'docs'
Requires-Dist: sphinx>=1.5; extra == 'docs'
